benchscofi/ALSWR.py
benchscofi/BNNR.py
benchscofi/Constant.py
benchscofi/DDA_SKF.py
benchscofi/DRRS.py
benchscofi/FFMWrapper.py
benchscofi/FastaiCollabWrapper.py
benchscofi/HAN.py
benchscofi/LRSSL.py
benchscofi/LibMF.py
benchscofi/LibMFWrapper.py
benchscofi/LogisticMF.py
benchscofi/MBiRW.py
benchscofi/NIMCGCN.py
benchscofi/PMF.py
benchscofi/PSGCN.py
benchscofi/PUextraTrees.py
benchscofi/PulearnWrapper.py
benchscofi/SCPMF.py
benchscofi/SimpleBinaryClassifier.py
benchscofi/SimplePULearning.py
benchscofi/VariationalWrapper.py
benchscofi/XGBoost.py
benchscofi/__init__.py
benchscofi/implementations/AlternatingLeastSquares.py
benchscofi/implementations/BayesianPairwiseRanking.py
benchscofi/implementations/HANImplementation.py
benchscofi/implementations/LogisticMatrixFactorization.py
benchscofi/implementations/NIMCGCNImplementation.py
benchscofi/implementations/PSGCNImplementation.py
benchscofi/implementations/PUextraTreeImplementation.py
benchscofi/implementations/VariationalInference.py
benchscofi/implementations/__init__.py
benchscofi/utils/__init__.py
benchscofi/utils/prior_estimation.py
benchscofi/utils/rowwise_metrics.py
benchscofi-2.0.1.dist-info/METADATA
benchscofi-2.0.1.dist-info/WHEEL
benchscofi-2.0.1.dist-info/top_level.txt
benchscofi-2.0.1.dist-info/RECORD
