Metadata-Version: 2.2
Name: benchscofi
Version: 2.0.1
Summary: Package which contains implementations of published collaborative filtering-based algorithms for drug repurposing.
Home-page: https://github.com/RECeSS-EU-Project/benchscofi
Author: Clémence Réda
Author-email: recess-project@proton.me
Classifier: Intended Audience :: Science/Research
Classifier: Topic :: Scientific/Engineering
Classifier: Topic :: Scientific/Engineering :: Artificial Intelligence
Classifier: License :: OSI Approved :: MIT License
Requires-Python: >=3.8.5
Requires-Dist: stanscofi>=2.0.0
Requires-Dist: tensorflow==2.4.3
Requires-Dist: pulearn>=0.0.7
Requires-Dist: torch>=2.0.1
Requires-Dist: spacy==3.7.6
Requires-Dist: fastai>=2.7.12
Requires-Dist: torch_geometric>=2.3.1
Requires-Dist: pyFFM
Requires-Dist: protobuf==3.9.*
Requires-Dist: pydantic==1.9.*
Requires-Dist: pytorch-lightning<2.0.0
Requires-Dist: torchmetrics
Requires-Dist: numpy==1.19.4
Requires-Dist: scikit-learn==1.2.*
Requires-Dist: dgl>=1.1.1
Requires-Dist: libmf>=0.9.2
Requires-Dist: xgboost>=2.0.2
Dynamic: author
Dynamic: author-email
Dynamic: classifier
Dynamic: description
Dynamic: description-content-type
Dynamic: home-page
Dynamic: keywords
Dynamic: requires-dist
Dynamic: requires-python
Dynamic: summary
